autoconfsh/__init__.py
autoconfsh/__main__.py
autoconfsh/cli.py
autoconfsh-0.0.2.dist-info/LICENSE
autoconfsh-0.0.2.dist-info/METADATA
autoconfsh-0.0.2.dist-info/WHEEL
autoconfsh-0.0.2.dist-info/entry_points.txt
autoconfsh-0.0.2.dist-info/top_level.txt
autoconfsh-0.0.2.dist-info/RECORD
