Metadata-Version: 2.1
Name: autoconfsh
Version: 0.0.2
Summary: Autoconf.sh - the lazy mans bootstrapper for Arch Linux
Home-page: https://github.com/jakeobsen/autoconf.sh
Author: Morten Jakeobsen
Author-email: morten@jakeobsen.com
License: UNKNOWN
Project-URL: Bug Reports, https://github.com/jakeobsen/autoconf.sh/issues
Project-URL: Source, https://github.com/jakeobsen/autoconf.sh
Keywords: arch,linux,bootstrap,bootstrapping,arch linux,installer,install,automate,automation
Platform: UNKNOWN
Classifier: Development Status :: 3 - Alpha
Classifier: Intended Audience :: System Administrators
Classifier: Topic :: System :: Installation/Setup
Classifier: License :: OSI Approved :: BSD License
Classifier: Programming Language :: Python :: 3
Classifier: Programming Language :: Python :: 3.9
Classifier: Programming Language :: Python :: 3 :: Only
Requires-Python: >=3.9, <4
License-File: LICENSE
